README
setup.py
setup2.py
startmenu_snapshot.py
startmenu_snapshot.egg-info/PKG-INFO
startmenu_snapshot.egg-info/SOURCES.txt
startmenu_snapshot.egg-info/dependency_links.txt
startmenu_snapshot.egg-info/not-zip-safe
startmenu_snapshot.egg-info/requires.txt
startmenu_snapshot.egg-info/top_level.txt